cavs_style/__about__.py
cavs_style/__init__.py
cavs_style/bitmap_cmaps.conf
cavs_style/colors.py
cavs_style/formatters.py
cavs_style/style.py
cavs_style/fonts/Chivo-Black.ttf
cavs_style/fonts/Chivo-BlackItalic.ttf
cavs_style/fonts/Chivo-Bold.ttf
cavs_style/fonts/Chivo-BoldItalic.ttf
cavs_style/fonts/Chivo-ExtraBold.ttf
cavs_style/fonts/Chivo-ExtraBoldItalic.ttf
cavs_style/fonts/Chivo-Italic.ttf
cavs_style/fonts/Chivo-Light.ttf
cavs_style/fonts/Chivo-LightItalic.ttf
cavs_style/fonts/Chivo-Medium.ttf
cavs_style/fonts/Chivo-MediumItalic.ttf
cavs_style/fonts/Chivo-Regular.ttf
cavs_style/fonts/Chivo-Thin.ttf
cavs_style/fonts/Chivo-ThinItalic.ttf
cavs_style/fonts/OFL.txt
cavs_style-0.1.0.dist-info/METADATA
cavs_style-0.1.0.dist-info/WHEEL
cavs_style-0.1.0.dist-info/licenses/LICENSE.txt
cavs_style-0.1.0.dist-info/RECORD
